{
  "name": "Henry Ortega",
  "age": 64,
  "address": {
    "street": "Zouwi Trail",
    "city": "Sojalebiz",
    "state": "NC",
    "zip": "82809"
  },
  "contact": {
    "phone": "(901) 634-5913",
    "servicePhone": "800532566"
  },
  "birthday": "1993-02-28T19:48:05.556Z",
  "ip": "222.124.147.242",
  "foo": "bar",
  "profile": {
    "about": "Newbo ticop dofo gu bodbop hi he vomu jehgeij wowan navtoga soso kuphugo vid de watzaw pacsanju dajishe. Ructon zitleglu cer zemtak hoh job or if odpibew tasupe nobakos pa eli hadef hacibmi bifel basha sidi. Zar keg za sawo nu bivuzwu tipu puadso kapiv zujendo oh fara malupe dungowugu. Fedav uhven lizas zat wew ho etbouce om dilmom ujuotigir cezukebe kepebpek tipelu polosuc dijuh larcag nevob cucugofi. La fubliwfi le ipvolupo to wezilmo le bonazba ze elo bephowaze nafakzo jub ija rupzagob luafe.",
    "bio": "Gobi ro kuutta ciprojij dehec bejverbir pabficdi veru sod neh jusus foz lolut. Ebbuh ajopuhfif gus pi dunecjoc fazzutgah puvrewej icunazu febjem pejoftun usi tasapjo avehu ta ti mi met. Obbu mow bunseb ifeiluazo netwo salri ma simafhac at pebsoh rokisjeb zaswuwo diguzviv jasubew cacec lo uza."
  },
  "apiKey": "a48387399232d2ae558fc050c3750435da6c21172d0d219df9429644f8c0bebe",
  "currency": {
    "code": "MWK",
    "name": "Malawi Kwacha"
  }
}