{
  "name": "Rosetta Curry",
  "age": 56,
  "address": {
    "street": "Gogu Extension",
    "city": "Fiabavup",
    "state": "MN",
    "zip": "52265"
  },
  "contact": {
    "phone": "(341) 709-8901",
    "servicePhone": "800673413"
  },
  "birthday": "1991-04-29T15:03:48.780Z",
  "ip": "129.29.241.190",
  "foo": "bar",
  "profile": {
    "about": "Ziezo hudibsap hekomuk gu le tarwih hojioh fil wubo caaguluc obamur hikor. Uwibillu cilsa is mucejam puwgu ludawwol hiz lo afabece zu codafgu ketebi wuf hajaik be wah havi lupor. Wunju lezo apebeud zoksej be tusev tebgihbot ca zoufu omi kisbecamo ri.",
    "bio": "Edabimkev to of tukukbuz zeswohfah togumicec ortufvo se nicu cis if asuhebo zohum dowiz carudfa lel ebtuglat. Bakfa ma wa liiwo foc luzodhi larol nafe kiizo gepba gepop om gomez taarunot. Tucokonit jizemed mof ze ve wouni ki viw fopapuw hojoka wehsapet he nulaw va racaz. Egguw be emcoece zebzapuw igowi ozokuzfe pibiwisu konur awsel ga recesgud ib wak re. Ki hunwe lipu cuv wo movejmuz cirjen dalnagog ko far akja dopitus vihis wa."
  },
  "apiKey": "00c2e4284b4e1d644fa848fa046e9794ea3eaa4728afc88096f9e75437b4e00a",
  "currency": {
    "code": "JPY",
    "name": "Japan Yen"
  }
}